bluezoo/__init__.py
bluezoo/adapter.py
bluezoo/bluezoo.py
bluezoo/controller.py
bluezoo/device.py
bluezoo/events.py
bluezoo/exceptions.py
bluezoo/log.py
bluezoo/root.py
bluezoo/utils.py
bluezoo/adv/__init__.py
bluezoo/adv/manager.py
bluezoo/gatt/__init__.py
bluezoo/gatt/application.py
bluezoo/gatt/characteristic.py
bluezoo/gatt/descriptor.py
bluezoo/gatt/manager.py
bluezoo/gatt/service.py
bluezoo/interfaces/Adapter.py
bluezoo/interfaces/Agent.py
bluezoo/interfaces/AgentManager.py
bluezoo/interfaces/Device.py
bluezoo/interfaces/GattCharacteristic.py
bluezoo/interfaces/GattDescriptor.py
bluezoo/interfaces/GattManager.py
bluezoo/interfaces/GattService.py
bluezoo/interfaces/LEAdvertisement.py
bluezoo/interfaces/LEAdvertisingManager.py
bluezoo/interfaces/__init__.py
bluezoo-1.0.2.dist-info/licenses/LICENSE
bluezoo-1.0.2.dist-info/METADATA
bluezoo-1.0.2.dist-info/WHEEL
bluezoo-1.0.2.dist-info/entry_points.txt
bluezoo-1.0.2.dist-info/top_level.txt
bluezoo-1.0.2.dist-info/RECORD
