Metadata-Version: 2.4
Name: bluezoo
Version: 1.0.2
Summary: A mock for the BlueZ D-Bus API
License-Expression: GPL-2.0-only
Project-URL: Homepage, https://github.com/Samsung/BlueZoo
Classifier: Intended Audience :: Developers
Classifier: Operating System :: POSIX :: Linux
Classifier: Programming Language :: Python :: 3
Classifier: Topic :: Software Development :: Testing
Classifier: Topic :: Software Development :: Testing :: Mocking
Requires-Python: >=3.11
License-File: LICENSE
Requires-Dist: coloredlogs>=6.0.0
Requires-Dist: pyventus>=0.7.0
Requires-Dist: pyparsing>=3.0.0
Requires-Dist: sdbus>=0.14.1
Dynamic: license-file
